marquise_cffi
marquise
