Metadata-Version: 1.0
Name: marquise
Version: 0.2.1
Summary: Python bindings for libmarquise
Home-page: https://github.com/anchor/pymarquise
Author: Anchor Engineering
Author-email: engineering@anchor.net.au
License: UNKNOWN
Platform: UNKNOWN
